django_fixtures_command/__init__.py
django_fixtures_command/apps.py
django_fixtures_command/management/__init__.py
django_fixtures_command/management/commands/__init__.py
django_fixtures_command/management/commands/fixtures.py
django_fixtures_command-0.1.0.dist-info/LICENSE
django_fixtures_command-0.1.0.dist-info/METADATA
django_fixtures_command-0.1.0.dist-info/WHEEL
django_fixtures_command-0.1.0.dist-info/top_level.txt
django_fixtures_command-0.1.0.dist-info/RECORD
