Metadata-Version: 2.1
Name: django-fixtures-command
Version: 0.1.0
Summary: Simple Django command that helps to organize your fixtures
Home-page: https://github.com/marcinjosinski/django-fixtures-command
Author: Marcin Josiński
Author-email: josinski@outlook.com
License: MIT
Keywords: Django
Platform: UNKNOWN
Classifier: Development Status :: 3 - Alpha
Classifier: Framework :: Django :: 3.0
Classifier: Framework :: Django :: 3.1
Classifier: Intended Audience :: Developers
Classifier: License :: OSI Approved :: MIT License
Classifier: Natural Language :: English
Classifier: Operating System :: OS Independent
Classifier: Programming Language :: Python :: 3 :: Only
Classifier: Programming Language :: Python :: 3.8
Classifier: Programming Language :: Python :: 3.9
Requires-Python: >=3.8
Requires-Dist: Django (>=3.0)
